LICENSE
freshwater/__init__.py
freshwater/constants.py
freshwater/eos.py
freshwater-0.1.5.dist-info/LICENSE
freshwater-0.1.5.dist-info/WHEEL
freshwater-0.1.5.dist-info/METADATA
freshwater-0.1.5.dist-info/RECORD
