Metadata-Version: 2.1
Name: freshwater
Version: 0.1.5
Summary: Python module for estimating thermodynamic properties of water in freshwater lakes.
Home-page: https://github.com/danielrobb/freshwater
License: MIT
Keywords: limnology,density,water,equation of state
Author: danielrobb
Author-email: danielrobb@gmail.com
Requires-Python: >=3.7,<4.0
Classifier: Intended Audience :: Science/Research
Classifier: License :: OSI Approved :: MIT License
Classifier: Programming Language :: Python :: 3
Classifier: Programming Language :: Python :: 3.7
Classifier: Programming Language :: Python :: 3.8
Classifier: Topic :: Scientific/Engineering :: Hydrology
Requires-Dist: numpy (>=1.19.1,<2.0.0)
Project-URL: Documentation, https://danielrobb.github.io/freshwater/
Project-URL: Repository, https://github.com/danielrobb/freshwater
